wskill/__init__.py
wskill/cli.py
wskill/core.py
wskill/mcp_server.py
wskill/online.py
wskill-1.1.0.dist-info/licenses/LICENSE
wskill-1.1.0.dist-info/METADATA
wskill-1.1.0.dist-info/WHEEL
wskill-1.1.0.dist-info/entry_points.txt
wskill-1.1.0.dist-info/top_level.txt
wskill-1.1.0.dist-info/RECORD
