Metadata-Version: 2.4
Name: wskill
Version: 1.1.0
Summary: Windsurf Skill Manager - 搜索和管理Windsurf技能的命令行工具
Author-email: ChuanKang <chuankangkk@example.com>
License: MIT
Project-URL: Homepage, https://github.com/1837620622/wskill
Project-URL: Documentation, https://github.com/1837620622/wskill#readme
Keywords: windsurf,skill,cli,search,cascade
Classifier: Development Status :: 4 - Beta
Classifier: Environment :: Console
Classifier: Intended Audience :: Developers
Classifier: License :: OSI Approved :: MIT License
Classifier: Operating System :: OS Independent
Classifier: Programming Language :: Python :: 3
Classifier: Programming Language :: Python :: 3.8
Classifier: Programming Language :: Python :: 3.9
Classifier: Programming Language :: Python :: 3.10
Classifier: Programming Language :: Python :: 3.11
Classifier: Programming Language :: Python :: 3.12
Classifier: Topic :: Utilities
Requires-Python: >=3.10
License-File: LICENSE
Requires-Dist: pyyaml>=6.0
Requires-Dist: mcp>=1.0.0
Dynamic: license-file
